win11toast.py
win11toast-0.36.1.dist-info/licenses/LICENSE
win11toast-0.36.1.dist-info/METADATA
win11toast-0.36.1.dist-info/WHEEL
win11toast-0.36.1.dist-info/top_level.txt
win11toast-0.36.1.dist-info/RECORD
