Metadata-Version: 2.4
Name: win11toast
Version: 0.36.1
Summary: Toast notifications for Windows 10 and 11
Home-page: https://github.com/GitHub30/win11toast
Author: Tomofumi Inoue
Author-email: funaox@gmail.com
License: MIT
Project-URL: Bug Tracker, https://github.com/GitHub30/win11toast/issues
Classifier: Programming Language :: Python :: 3
Classifier: License :: OSI Approved :: MIT License
Classifier: Topic :: Utilities
Classifier: Operating System :: Microsoft
Classifier: Operating System :: Microsoft :: Windows :: Windows 10
Classifier: Operating System :: Microsoft :: Windows :: Windows 11
License-File: LICENSE
Requires-Dist: winrt-Windows.Data.Xml.Dom
Requires-Dist: winrt-Windows.Foundation
Requires-Dist: winrt.windows.Foundation.Collections
Requires-Dist: winrt-Windows.Globalization
Requires-Dist: winrt-Windows.Graphics.Imaging
Requires-Dist: winrt-Windows.Media.Core
Requires-Dist: winrt-Windows.Media.Ocr
Requires-Dist: winrt-Windows.Media.Playback
Requires-Dist: winrt-Windows.Media.Speechsynthesis
Requires-Dist: winrt-Windows.Storage
Requires-Dist: winrt-Windows.Storage.Streams
Requires-Dist: winrt-Windows.UI.Notifications
Dynamic: author
Dynamic: author-email
Dynamic: classifier
Dynamic: description
Dynamic: description-content-type
Dynamic: home-page
Dynamic: license
Dynamic: license-file
Dynamic: project-url
Dynamic: requires-dist
Dynamic: summary
